[
  {
    "id": "minecraft:all_black",
    "data": {
      "asset_id": "minecraft:entity/cat/cat_all_black",
      "baby_asset_id": "minecraft:entity/cat/cat_all_black_baby",
      "spawn_conditions": [
        {
          "condition": {
            "type": "minecraft:structure",
            "structures": "#minecraft:cats_spawn_as_black"
          },
          "priority": 1
        },
        {
          "condition": {
            "type": "minecraft:moon_brightness",
            "range": {
              "min": 0.9
            }
          },
          "priority": 0
        }
      ]
    }
  },
  {
    "id": "minecraft:black",
    "data": {
      "asset_id": "minecraft:entity/cat/cat_black",
      "baby_asset_id": "minecraft:entity/cat/cat_black_baby",
      "spawn_conditions": [
        {
          "priority": 0
        }
      ]
    }
  },
  {
    "id": "minecraft:british_shorthair",
    "data": {
      "asset_id": "minecraft:entity/cat/cat_british_shorthair",
      "baby_asset_id": "minecraft:entity/cat/cat_british_shorthair_baby",
      "spawn_conditions": [
        {
          "priority": 0
        }
      ]
    }
  },
  {
    "id": "minecraft:calico",
    "data": {
      "asset_id": "minecraft:entity/cat/cat_calico",
      "baby_asset_id": "minecraft:entity/cat/cat_calico_baby",
      "spawn_conditions": [
        {
          "priority": 0
        }
      ]
    }
  },
  {
    "id": "minecraft:jellie",
    "data": {
      "asset_id": "minecraft:entity/cat/cat_jellie",
      "baby_asset_id": "minecraft:entity/cat/cat_jellie_baby",
      "spawn_conditions": [
        {
          "priority": 0
        }
      ]
    }
  },
  {
    "id": "minecraft:persian",
    "data": {
      "asset_id": "minecraft:entity/cat/cat_persian",
      "baby_asset_id": "minecraft:entity/cat/cat_persian_baby",
      "spawn_conditions": [
        {
          "priority": 0
        }
      ]
    }
  },
  {
    "id": "minecraft:ragdoll",
    "data": {
      "asset_id": "minecraft:entity/cat/cat_ragdoll",
      "baby_asset_id": "minecraft:entity/cat/cat_ragdoll_baby",
      "spawn_conditions": [
        {
          "priority": 0
        }
      ]
    }
  },
  {
    "id": "minecraft:red",
    "data": {
      "asset_id": "minecraft:entity/cat/cat_red",
      "baby_asset_id": "minecraft:entity/cat/cat_red_baby",
      "spawn_conditions": [
        {
          "priority": 0
        }
      ]
    }
  },
  {
    "id": "minecraft:siamese",
    "data": {
      "asset_id": "minecraft:entity/cat/cat_siamese",
      "baby_asset_id": "minecraft:entity/cat/cat_siamese_baby",
      "spawn_conditions": [
        {
          "priority": 0
        }
      ]
    }
  },
  {
    "id": "minecraft:tabby",
    "data": {
      "asset_id": "minecraft:entity/cat/cat_tabby",
      "baby_asset_id": "minecraft:entity/cat/cat_tabby_baby",
      "spawn_conditions": [
        {
          "priority": 0
        }
      ]
    }
  },
  {
    "id": "minecraft:white",
    "data": {
      "asset_id": "minecraft:entity/cat/cat_white",
      "baby_asset_id": "minecraft:entity/cat/cat_white_baby",
      "spawn_conditions": [
        {
          "priority": 0
        }
      ]
    }
  }
]